[
    {
        "t": 0,
        "value": 0.29743240980921015
    },
    {
        "t": 1,
        "value": 0.9404817007952807
    },
    {
        "t": 2,
        "value": 0.28605921880503504
    },
    {
        "t": 3,
        "value": 0.749363801754012
    },
    {
        "t": 4,
        "value": 0.7612930271820035
    },
    {
        "t": 5,
        "value": 0.18829441295892668
    },
    {
        "t": 6,
        "value": 0.8206603784695431
    },
    {
        "t": 7,
        "value": 0.6938495237551354
    },
    {
        "t": 8,
        "value": 0.5323739204318444
    },
    {
        "t": 9,
        "value": 0.7410346090464479
    },
    {
        "t": 10,
        "value": 0.043396578655874984
    },
    {
        "t": 11,
        "value": 0.9983171834020277
    },
    {
        "t": 12,
        "value": 0.20260508373389163
    },
    {
        "t": 13,
        "value": 0.19468254738495228
    },
    {
        "t": 14,
        "value": 0.6995563489905903
    },
    {
        "t": 15,
        "value": 0.3157538527165199
    },
    {
        "t": 16,
        "value": 0.16322067986376165
    },
    {
        "t": 17,
        "value": 0.35879428288196213
    },
    {
        "t": 18,
        "value": 0.17147087408759898
    },
    {
        "t": 19,
        "value": 0.40889713652470816
    },
    {
        "t": 20,
        "value": 0.153908742744565
    },
    {
        "t": 21,
        "value": 0.4010986860751904
    },
    {
        "t": 22,
        "value": 0.5065171266680395
    },
    {
        "t": 23,
        "value": 0.5502667910781698
    },
    {
        "t": 24,
        "value": 0.9227252285527715
    },
    {
        "t": 25,
        "value": 0.04069014187076292
    },
    {
        "t": 26,
        "value": 0.7858096529490299
    },
    {
        "t": 27,
        "value": 0.48184449370885396
    },
    {
        "t": 28,
        "value": 0.7384345856922581
    },
    {
        "t": 29,
        "value": 0.19052098897408298
    },
    {
        "t": 30,
        "value": 0.11299736640976121
    },
    {
        "t": 31,
        "value": 0.16317436429079302
    },
    {
        "t": 32,
        "value": 0.7160201109139457
    },
    {
        "t": 33,
        "value": 0.5318721648309013
    },
    {
        "t": 34,
        "value": 0.8680224255468765
    },
    {
        "t": 35,
        "value": 0.36905678239474116
    },
    {
        "t": 36,
        "value": 0.6514951162701007
    },
    {
        "t": 37,
        "value": 0.12544433240430486
    },
    {
        "t": 38,
        "value": 0.93936764006897
    },
    {
        "t": 39,
        "value": 0.12331531125425876
    },
    {
        "t": 40,
        "value": 0.23106409789907756
    },
    {
        "t": 41,
        "value": 0.2573568286565793
    },
    {
        "t": 42,
        "value": 0.4826026344600455
    },
    {
        "t": 43,
        "value": 0.14831716143357077
    },
    {
        "t": 44,
        "value": 0.5261399294187408
    },
    {
        "t": 45,
        "value": 0.18873245931398708
    },
    {
        "t": 46,
        "value": 0.35627531923107514
    },
    {
        "t": 47,
        "value": 0.6079198494370363
    },
    {
        "t": 48,
        "value": 0.5868354600044787
    },
    {
        "t": 49,
        "value": 0.3592655384057447
    },
    {
        "t": 50,
        "value": 0.6995868880236803
    },
    {
        "t": 51,
        "value": 0.9424646779852316
    },
    {
        "t": 52,
        "value": 0.3669891723797236
    },
    {
        "t": 53,
        "value": 0.12966287999246917
    },
    {
        "t": 54,
        "value": 0.25451884882504605
    },
    {
        "t": 55,
        "value": 0.47933939605654285
    },
    {
        "t": 56,
        "value": 0.08772114049557478
    },
    {
        "t": 57,
        "value": 0.07766884600183244
    },
    {
        "t": 58,
        "value": 0.2233546619644594
    },
    {
        "t": 59,
        "value": 0.030624847680458922
    },
    {
        "t": 60,
        "value": 0.7462496024979197
    },
    {
        "t": 61,
        "value": 0.8520532582054725
    },
    {
        "t": 62,
        "value": 0.2197800738967728
    },
    {
        "t": 63,
        "value": 0.10047292530466434
    },
    {
        "t": 64,
        "value": 0.018956515627365667
    },
    {
        "t": 65,
        "value": 0.39539582755237557
    },
    {
        "t": 66,
        "value": 0.03500264938201325
    },
    {
        "t": 67,
        "value": 0.4616632380029969
    },
    {
        "t": 68,
        "value": 0.9444243524036574
    },
    {
        "t": 69,
        "value": 0.6545561239038116
    },
    {
        "t": 70,
        "value": 0.16572157705271484
    },
    {
        "t": 71,
        "value": 0.6338896420714275
    },
    {
        "t": 72,
        "value": 0.5458239074472403
    },
    {
        "t": 73,
        "value": 0.15769727531970712
    },
    {
        "t": 74,
        "value": 0.7453711553472393
    },
    {
        "t": 75,
        "value": 0.70200208269564
    },
    {
        "t": 76,
        "value": 0.42076849726248944
    },
    {
        "t": 77,
        "value": 0.6766648225773577
    },
    {
        "t": 78,
        "value": 0.9637438292578812
    },
    {
        "t": 79,
        "value": 0.26335512772042424
    },
    {
        "t": 80,
        "value": 0.41545512603698187
    },
    {
        "t": 81,
        "value": 0.4219292682175977
    },
    {
        "t": 82,
        "value": 0.7129135579577476
    },
    {
        "t": 83,
        "value": 0.30464712104081004
    },
    {
        "t": 84,
        "value": 0.05871623802110104
    },
    {
        "t": 85,
        "value": 0.45815722545265625
    },
    {
        "t": 86,
        "value": 0.7976042708745984
    },
    {
        "t": 87,
        "value": 0.6944982070968845
    },
    {
        "t": 88,
        "value": 0.13407324201682302
    },
    {
        "t": 89,
        "value": 0.7923873927508552
    },
    {
        "t": 90,
        "value": 0.7263675553724916
    },
    {
        "t": 91,
        "value": 0.17318742026200762
    },
    {
        "t": 92,
        "value": 0.3970883763325618
    },
    {
        "t": 93,
        "value": 0.6891715158629995
    },
    {
        "t": 94,
        "value": 0.21896703185821642
    },
    {
        "t": 95,
        "value": 0.34519900470325593
    },
    {
        "t": 96,
        "value": 0.5221411256865867
    },
    {
        "t": 97,
        "value": 0.7674459526167129
    },
    {
        "t": 98,
        "value": 0.8000985663345712
    },
    {
        "t": 99,
        "value": 0.7816016913706028
    },
    {
        "t": 100,
        "value": 0.9671438079723513
    },
    {
        "t": 101,
        "value": 0.9369476036225002
    },
    {
        "t": 102,
        "value": 0.5492118599306767
    },
    {
        "t": 103,
        "value": 0.2716670173747264
    },
    {
        "t": 104,
        "value": 0.729217840935823
    },
    {
        "t": 105,
        "value": 0.4922651305739357
    },
    {
        "t": 106,
        "value": 0.5576703337766992
    },
    {
        "t": 107,
        "value": 0.028756442564863538
    },
    {
        "t": 108,
        "value": 0.41597832968617343
    },
    {
        "t": 109,
        "value": 0.7493966957305217
    },
    {
        "t": 110,
        "value": 0.691638121281645
    },
    {
        "t": 111,
        "value": 0.3155117013162776
    },
    {
        "t": 112,
        "value": 0.7986372190123276
    },
    {
        "t": 113,
        "value": 0.09473742104596794
    },
    {
        "t": 114,
        "value": 0.4642629234289789
    },
    {
        "t": 115,
        "value": 0.4556494684259623
    },
    {
        "t": 116,
        "value": 0.8523985556282317
    },
    {
        "t": 117,
        "value": 0.09735281252580408
    },
    {
        "t": 118,
        "value": 0.5996511763076514
    },
    {
        "t": 119,
        "value": 0.05360841784023718
    },
    {
        "t": 120,
        "value": 0.6746325221797972
    },
    {
        "t": 121,
        "value": 0.5261634611229924
    },
    {
        "t": 122,
        "value": 0.9548446958648882
    },
    {
        "t": 123,
        "value": 0.6903684150649764
    },
    {
        "t": 124,
        "value": 0.7690776164116588
    },
    {
        "t": 125,
        "value": 0.5214508912267337
    },
    {
        "t": 126,
        "value": 0.264591496918834
    },
    {
        "t": 127,
        "value": 0.7448330008369753
    },
    {
        "t": 128,
        "value": 0.5861722986825464
    },
    {
        "t": 129,
        "value": 0.025457809431246536
    },
    {
        "t": 130,
        "value": 0.6968495800841036
    },
    {
        "t": 131,
        "value": 0.1214739971337373
    },
    {
        "t": 132,
        "value": 0.8530500406304881
    },
    {
        "t": 133,
        "value": 0.8116940674108328
    },
    {
        "t": 134,
        "value": 0.6966284518308092
    },
    {
        "t": 135,
        "value": 0.44915270683811503
    },
    {
        "t": 136,
        "value": 0.30355531988255235
    },
    {
        "t": 137,
        "value": 0.7341853124541594
    },
    {
        "t": 138,
        "value": 0.7139812860620333
    },
    {
        "t": 139,
        "value": 0.2554488040939745
    },
    {
        "t": 140,
        "value": 0.4241970578573091
    },
    {
        "t": 141,
        "value": 0.42723787773129596
    },
    {
        "t": 142,
        "value": 0.8636874975579459
    },
    {
        "t": 143,
        "value": 0.11866967158421449
    },
    {
        "t": 144,
        "value": 0.310415122656994
    },
    {
        "t": 145,
        "value": 0.5596548892101705
    },
    {
        "t": 146,
        "value": 0.7683957251260445
    },
    {
        "t": 147,
        "value": 0.04211548587709879
    },
    {
        "t": 148,
        "value": 0.4862782756430364
    },
    {
        "t": 149,
        "value": 0.6140592186672592
    },
    {
        "t": 150,
        "value": 0.28038864494444904
    },
    {
        "t": 151,
        "value": 0.6971659410929315
    },
    {
        "t": 152,
        "value": 0.8398767145595728
    },
    {
        "t": 153,
        "value": 0.6963126834240015
    },
    {
        "t": 154,
        "value": 0.6277630516268583
    },
    {
        "t": 155,
        "value": 0.5624035171104981
    },
    {
        "t": 156,
        "value": 0.9813844247068502
    },
    {
        "t": 157,
        "value": 0.7309513886062551
    },
    {
        "t": 158,
        "value": 0.8188294822558486
    },
    {
        "t": 159,
        "value": 0.01652985316304567
    },
    {
        "t": 160,
        "value": 0.03300615724673561
    },
    {
        "t": 161,
        "value": 0.8125766458201493
    },
    {
        "t": 162,
        "value": 0.7290921558533779
    },
    {
        "t": 163,
        "value": 0.10679252460606836
    },
    {
        "t": 164,
        "value": 0.73002600591695
    },
    {
        "t": 165,
        "value": 0.4584867244000427
    },
    {
        "t": 166,
        "value": 0.782107457303711
    },
    {
        "t": 167,
        "value": 0.26724406608998397
    },
    {
        "t": 168,
        "value": 0.6462735996374144
    },
    {
        "t": 169,
        "value": 0.30068413044121833
    },
    {
        "t": 170,
        "value": 0.8828520079626647
    },
    {
        "t": 171,
        "value": 0.37069134313984686
    },
    {
        "t": 172,
        "value": 0.14162019541864657
    },
    {
        "t": 173,
        "value": 0.2818473216223173
    },
    {
        "t": 174,
        "value": 0.4643361337397236
    },
    {
        "t": 175,
        "value": 0.7110354910999557
    },
    {
        "t": 176,
        "value": 0.6375875525896036
    },
    {
        "t": 177,
        "value": 0.8866959598467979
    },
    {
        "t": 178,
        "value": 0.2610730030752131
    },
    {
        "t": 179,
        "value": 0.7382620336017821
    },
    {
        "t": 180,
        "value": 0.2734452518668291
    },
    {
        "t": 181,
        "value": 0.5510000458504588
    },
    {
        "t": 182,
        "value": 0.4590885484547256
    },
    {
        "t": 183,
        "value": 0.7731771499093519
    },
    {
        "t": 184,
        "value": 0.19751566496437756
    },
    {
        "t": 185,
        "value": 0.8785680083048294
    },
    {
        "t": 186,
        "value": 0.032096928733368446
    },
    {
        "t": 187,
        "value": 0.6127717038000201
    },
    {
        "t": 188,
        "value": 0.45393317130540434
    },
    {
        "t": 189,
        "value": 0.2227616775550202
    },
    {
        "t": 190,
        "value": 0.7805205515081655
    },
    {
        "t": 191,
        "value": 0.14706723680021472
    },
    {
        "t": 192,
        "value": 0.5931721845350189
    },
    {
        "t": 193,
        "value": 0.6526265705798323
    },
    {
        "t": 194,
        "value": 0.7236218536868172
    },
    {
        "t": 195,
        "value": 0.5806589038775917
    },
    {
        "t": 196,
        "value": 0.8558995544692322
    },
    {
        "t": 197,
        "value": 0.12807343254782844
    },
    {
        "t": 198,
        "value": 0.4985515930878557
    },
    {
        "t": 199,
        "value": 0.45269547033329893
    },
    {
        "t": 200,
        "value": 0.5471871464423327
    },
    {
        "t": 201,
        "value": 0.3609447732375024
    },
    {
        "t": 202,
        "value": 0.08544053492313042
    },
    {
        "t": 203,
        "value": 0.9464735715847696
    },
    {
        "t": 204,
        "value": 0.11910971711800011
    },
    {
        "t": 205,
        "value": 0.7561461506904089
    },
    {
        "t": 206,
        "value": 0.936515948117113
    },
    {
        "t": 207,
        "value": 0.9955591332232115
    },
    {
        "t": 208,
        "value": 0.7058166465234723
    },
    {
        "t": 209,
        "value": 0.1242729457640337
    },
    {
        "t": 210,
        "value": 0.1968405796185957
    },
    {
        "t": 211,
        "value": 0.1257113223029258
    },
    {
        "t": 212,
        "value": 0.5029499349956899
    },
    {
        "t": 213,
        "value": 0.9687138661030675
    },
    {
        "t": 214,
        "value": 0.761894021201264
    },
    {
        "t": 215,
        "value": 0.3302427644921201
    },
    {
        "t": 216,
        "value": 0.19836207022720942
    },
    {
        "t": 217,
        "value": 0.387630534281156
    },
    {
        "t": 218,
        "value": 0.5292006871745445
    },
    {
        "t": 219,
        "value": 0.8303973877358892
    },
    {
        "t": 220,
        "value": 0.31787907097941326
    },
    {
        "t": 221,
        "value": 0.7622056926421089
    },
    {
        "t": 222,
        "value": 0.04698826037548609
    },
    {
        "t": 223,
        "value": 0.5476861442268502
    },
    {
        "t": 224,
        "value": 0.8767818493257401
    },
    {
        "t": 225,
        "value": 0.0425175164367011
    },
    {
        "t": 226,
        "value": 0.5020409438689617
    },
    {
        "t": 227,
        "value": 0.04836071056627489
    },
    {
        "t": 228,
        "value": 0.05520495377894741
    },
    {
        "t": 229,
        "value": 0.33008747736484145
    },
    {
        "t": 230,
        "value": 0.53887859272728
    },
    {
        "t": 231,
        "value": 0.8030297776117428
    },
    {
        "t": 232,
        "value": 0.7278330832594802
    },
    {
        "t": 233,
        "value": 0.0014988583642338016
    },
    {
        "t": 234,
        "value": 0.5232939422721372
    },
    {
        "t": 235,
        "value": 0.4748093375772944
    },
    {
        "t": 236,
        "value": 0.22683122225293006
    },
    {
        "t": 237,
        "value": 0.840072641068395
    },
    {
        "t": 238,
        "value": 0.3623878094840074
    },
    {
        "t": 239,
        "value": 0.3243226034316318
    },
    {
        "t": 240,
        "value": 0.5612331014134955
    },
    {
        "t": 241,
        "value": 0.7068520751433247
    },
    {
        "t": 242,
        "value": 0.003986177428946247
    },
    {
        "t": 243,
        "value": 0.9593587403513949
    },
    {
        "t": 244,
        "value": 0.22300705587848824
    },
    {
        "t": 245,
        "value": 0.9541227054119047
    },
    {
        "t": 246,
        "value": 0.9286074376778322
    },
    {
        "t": 247,
        "value": 0.7178768319279665
    },
    {
        "t": 248,
        "value": 0.39751509519399264
    },
    {
        "t": 249,
        "value": 0.7046164206824687
    },
    {
        "t": 250,
        "value": 0.30996736229859934
    },
    {
        "t": 251,
        "value": 0.012971583786636653
    },
    {
        "t": 252,
        "value": 0.6866355334713607
    },
    {
        "t": 253,
        "value": 0.759274165146885
    },
    {
        "t": 254,
        "value": 0.666117388128769
    },
    {
        "t": 255,
        "value": 0.367753302088188
    },
    {
        "t": 256,
        "value": 0.25325861515733483
    },
    {
        "t": 257,
        "value": 0.9514556024573976
    },
    {
        "t": 258,
        "value": 0.9945529438252114
    },
    {
        "t": 259,
        "value": 0.28107549289066824
    },
    {
        "t": 260,
        "value": 0.36805385566244886
    },
    {
        "t": 261,
        "value": 0.4368529112663503
    },
    {
        "t": 262,
        "value": 0.4142949375617807
    },
    {
        "t": 263,
        "value": 0.9270837008450972
    },
    {
        "t": 264,
        "value": 0.9801316136895097
    },
    {
        "t": 265,
        "value": 0.3849778451512269
    },
    {
        "t": 266,
        "value": 0.6377110559887748
    },
    {
        "t": 267,
        "value": 0.6389396616381356
    },
    {
        "t": 268,
        "value": 0.6822713414226141
    },
    {
        "t": 269,
        "value": 0.1791910700763656
    },
    {
        "t": 270,
        "value": 0.6346741950020464
    },
    {
        "t": 271,
        "value": 0.018363185417858863
    },
    {
        "t": 272,
        "value": 0.10291864219177593
    },
    {
        "t": 273,
        "value": 0.10423449683654651
    },
    {
        "t": 274,
        "value": 0.5574599668315763
    },
    {
        "t": 275,
        "value": 0.7009464501014206
    },
    {
        "t": 276,
        "value": 0.9688495830018309
    },
    {
        "t": 277,
        "value": 0.2415417060804108
    },
    {
        "t": 278,
        "value": 0.9572271526783587
    },
    {
        "t": 279,
        "value": 0.7025487886021966
    },
    {
        "t": 280,
        "value": 0.04597307358280289
    },
    {
        "t": 281,
        "value": 0.9670309818821218
    },
    {
        "t": 282,
        "value": 0.02550425460061767
    },
    {
        "t": 283,
        "value": 0.6397240597147622
    },
    {
        "t": 284,
        "value": 0.8732278437591536
    },
    {
        "t": 285,
        "value": 0.12690906899001642
    },
    {
        "t": 286,
        "value": 0.49337758900328654
    },
    {
        "t": 287,
        "value": 0.4096192388999377
    },
    {
        "t": 288,
        "value": 0.17908615429680297
    },
    {
        "t": 289,
        "value": 0.36274363069901716
    },
    {
        "t": 290,
        "value": 0.9129356825336096
    },
    {
        "t": 291,
        "value": 0.8474838916064844
    },
    {
        "t": 292,
        "value": 0.0007318816311855381
    },
    {
        "t": 293,
        "value": 0.49469790791766177
    },
    {
        "t": 294,
        "value": 0.2002217486349025
    },
    {
        "t": 295,
        "value": 0.7752625235412498
    },
    {
        "t": 296,
        "value": 0.211387352034054
    },
    {
        "t": 297,
        "value": 0.990219596671862
    },
    {
        "t": 298,
        "value": 0.4975289715762684
    },
    {
        "t": 299,
        "value": 0.5244746585553559
    },
    {
        "t": 300,
        "value": 0.28139616616093766
    },
    {
        "t": 301,
        "value": 0.14779220307093488
    },
    {
        "t": 302,
        "value": 0.4666951058374935
    },
    {
        "t": 303,
        "value": 0.4205477365478342
    },
    {
        "t": 304,
        "value": 0.2885324390291526
    },
    {
        "t": 305,
        "value": 0.734565039839702
    },
    {
        "t": 306,
        "value": 0.8016925860420244
    },
    {
        "t": 307,
        "value": 0.012908132172382736
    },
    {
        "t": 308,
        "value": 0.15262556065984778
    },
    {
        "t": 309,
        "value": 0.778597158271994
    },
    {
        "t": 310,
        "value": 0.30257081153847387
    },
    {
        "t": 311,
        "value": 0.6307531798513004
    },
    {
        "t": 312,
        "value": 0.6628329614732954
    },
    {
        "t": 313,
        "value": 0.8321844935438389
    },
    {
        "t": 314,
        "value": 0.08179528254965684
    },
    {
        "t": 315,
        "value": 0.6696540846281782
    },
    {
        "t": 316,
        "value": 0.2683060516216279
    },
    {
        "t": 317,
        "value": 0.3671402320100565
    },
    {
        "t": 318,
        "value": 0.5006852333699153
    },
    {
        "t": 319,
        "value": 0.7435102467278062
    },
    {
        "t": 320,
        "value": 0.03615472526532304
    },
    {
        "t": 321,
        "value": 0.619596197697307
    },
    {
        "t": 322,
        "value": 0.8255280871973413
    },
    {
        "t": 323,
        "value": 0.8276339875966816
    },
    {
        "t": 324,
        "value": 0.8762313558890653
    },
    {
        "t": 325,
        "value": 0.8939213265188348
    },
    {
        "t": 326,
        "value": 0.8678707865532255
    },
    {
        "t": 327,
        "value": 0.0028994731982155963
    },
    {
        "t": 328,
        "value": 0.00038831154760221587
    },
    {
        "t": 329,
        "value": 0.7245846030364957
    },
    {
        "t": 330,
        "value": 0.3242836763551814
    },
    {
        "t": 331,
        "value": 0.8446467330811186
    },
    {
        "t": 332,
        "value": 0.8215957907649727
    },
    {
        "t": 333,
        "value": 0.5858999543460546
    },
    {
        "t": 334,
        "value": 0.22717976915813287
    },
    {
        "t": 335,
        "value": 0.7675427509087783
    },
    {
        "t": 336,
        "value": 0.6396599435326984
    },
    {
        "t": 337,
        "value": 0.3681991240767136
    },
    {
        "t": 338,
        "value": 0.5578144327945688
    },
    {
        "t": 339,
        "value": 0.3985695715280433
    },
    {
        "t": 340,
        "value": 0.3856770887651958
    },
    {
        "t": 341,
        "value": 0.38704474483841167
    },
    {
        "t": 342,
        "value": 0.8210782948701899
    },
    {
        "t": 343,
        "value": 0.6809948948120917
    },
    {
        "t": 344,
        "value": 0.17041068283888428
    },
    {
        "t": 345,
        "value": 0.7878433880591741
    },
    {
        "t": 346,
        "value": 0.11749699064265506
    },
    {
        "t": 347,
        "value": 0.23514756051533459
    },
    {
        "t": 348,
        "value": 0.6074290814479505
    },
    {
        "t": 349,
        "value": 0.322733497090525
    },
    {
        "t": 350,
        "value": 0.687898793559851
    },
    {
        "t": 351,
        "value": 0.9777028976438819
    },
    {
        "t": 352,
        "value": 0.42251985126225866
    },
    {
        "t": 353,
        "value": 0.4361855120106608
    },
    {
        "t": 354,
        "value": 0.13506525747122577
    },
    {
        "t": 355,
        "value": 0.06558872316605013
    },
    {
        "t": 356,
        "value": 0.6876196763564912
    },
    {
        "t": 357,
        "value": 0.1726707267498373
    },
    {
        "t": 358,
        "value": 0.6001774859391659
    },
    {
        "t": 359,
        "value": 0.48446766377000006
    },
    {
        "t": 360,
        "value": 0.20236411354791817
    },
    {
        "t": 361,
        "value": 0.568068414292217
    },
    {
        "t": 362,
        "value": 0.9196871005406987
    },
    {
        "t": 363,
        "value": 0.2856359000246329
    },
    {
        "t": 364,
        "value": 0.5621205706539572
    },
    {
        "t": 365,
        "value": 0.01684713749919864
    },
    {
        "t": 366,
        "value": 0.6332379271551384
    },
    {
        "t": 367,
        "value": 0.7738988490112214
    },
    {
        "t": 368,
        "value": 0.7672613581437063
    },
    {
        "t": 369,
        "value": 0.22923645121411695
    },
    {
        "t": 370,
        "value": 0.8995081639200047
    },
    {
        "t": 371,
        "value": 0.12744311052057966
    },
    {
        "t": 372,
        "value": 0.3227255851015641
    },
    {
        "t": 373,
        "value": 0.666253172416157
    },
    {
        "t": 374,
        "value": 0.48051562109438983
    },
    {
        "t": 375,
        "value": 0.33821473661486745
    },
    {
        "t": 376,
        "value": 0.5305598145256539
    },
    {
        "t": 377,
        "value": 0.641648491333254
    },
    {
        "t": 378,
        "value": 0.5346488388819096
    },
    {
        "t": 379,
        "value": 0.7205674800867732
    },
    {
        "t": 380,
        "value": 0.1494035296361924
    },
    {
        "t": 381,
        "value": 0.2155305249445889
    },
    {
        "t": 382,
        "value": 0.28471594978153847
    },
    {
        "t": 383,
        "value": 0.17745025813782755
    },
    {
        "t": 384,
        "value": 0.4361058196222486
    },
    {
        "t": 385,
        "value": 0.7809194528989357
    },
    {
        "t": 386,
        "value": 0.528741070073903
    },
    {
        "t": 387,
        "value": 0.6765183003582935
    },
    {
        "t": 388,
        "value": 0.23013777023595017
    },
    {
        "t": 389,
        "value": 0.7235290644031296
    },
    {
        "t": 390,
        "value": 0.6124435729473475
    },
    {
        "t": 391,
        "value": 0.6971244466794029
    },
    {
        "t": 392,
        "value": 0.9152281260234828
    },
    {
        "t": 393,
        "value": 0.7606779992476682
    },
    {
        "t": 394,
        "value": 0.9089421543041367
    },
    {
        "t": 395,
        "value": 0.8276347060580435
    },
    {
        "t": 396,
        "value": 0.6925997667316011
    },
    {
        "t": 397,
        "value": 0.5821589967594049
    },
    {
        "t": 398,
        "value": 0.719597124260946
    },
    {
        "t": 399,
        "value": 0.912495673781819
    },
    {
        "t": 400,
        "value": 0.24618248581734348
    },
    {
        "t": 401,
        "value": 0.27170546901409454
    },
    {
        "t": 402,
        "value": 0.917288471874068
    },
    {
        "t": 403,
        "value": 0.21400329743788815
    },
    {
        "t": 404,
        "value": 0.7093588117919432
    },
    {
        "t": 405,
        "value": 0.48969111450098834
    },
    {
        "t": 406,
        "value": 0.21842664542542356
    },
    {
        "t": 407,
        "value": 0.6563023224091893
    },
    {
        "t": 408,
        "value": 0.757824699383652
    },
    {
        "t": 409,
        "value": 0.41866638544789836
    },
    {
        "t": 410,
        "value": 0.3557250581984106
    },
    {
        "t": 411,
        "value": 0.569317337641547
    },
    {
        "t": 412,
        "value": 0.502709273574443
    },
    {
        "t": 413,
        "value": 0.46689335393742515
    },
    {
        "t": 414,
        "value": 0.9386329505416358
    },
    {
        "t": 415,
        "value": 0.4451576699962313
    },
    {
        "t": 416,
        "value": 0.2723876095076404
    },
    {
        "t": 417,
        "value": 0.14990703788942006
    },
    {
        "t": 418,
        "value": 0.009108759134289102
    },
    {
        "t": 419,
        "value": 0.34539717834191297
    },
    {
        "t": 420,
        "value": 0.38820335181250254
    },
    {
        "t": 421,
        "value": 0.5227408448931902
    },
    {
        "t": 422,
        "value": 0.6610223869079375
    },
    {
        "t": 423,
        "value": 0.9933645327355196
    },
    {
        "t": 424,
        "value": 0.5113137322805767
    },
    {
        "t": 425,
        "value": 0.534929811933158
    },
    {
        "t": 426,
        "value": 0.7246636516787923
    },
    {
        "t": 427,
        "value": 0.30240321417684746
    },
    {
        "t": 428,
        "value": 0.28504623053072375
    },
    {
        "t": 429,
        "value": 0.5807955706801216
    },
    {
        "t": 430,
        "value": 0.644699442015372
    },
    {
        "t": 431,
        "value": 0.3972169013041673
    },
    {
        "t": 432,
        "value": 0.36940157012002994
    },
    {
        "t": 433,
        "value": 0.8424394537649084
    },
    {
        "t": 434,
        "value": 0.939596042537243
    },
    {
        "t": 435,
        "value": 0.07743719250482362
    },
    {
        "t": 436,
        "value": 0.6795766003726458
    },
    {
        "t": 437,
        "value": 0.40185375773213006
    },
    {
        "t": 438,
        "value": 0.19423589002426478
    },
    {
        "t": 439,
        "value": 0.1349977750306386
    },
    {
        "t": 440,
        "value": 0.48389096346453664
    },
    {
        "t": 441,
        "value": 0.6392875008203294
    },
    {
        "t": 442,
        "value": 0.22788232015454257
    },
    {
        "t": 443,
        "value": 0.01730894331979893
    },
    {
        "t": 444,
        "value": 0.13224685179362583
    },
    {
        "t": 445,
        "value": 0.634158922818095
    },
    {
        "t": 446,
        "value": 0.19870024431839628
    },
    {
        "t": 447,
        "value": 0.5925693621419789
    },
    {
        "t": 448,
        "value": 0.4690610138906989
    },
    {
        "t": 449,
        "value": 0.911000000436976
    },
    {
        "t": 450,
        "value": 0.32653519778360596
    },
    {
        "t": 451,
        "value": 0.22717284698373819
    },
    {
        "t": 452,
        "value": 0.4821598122651395
    },
    {
        "t": 453,
        "value": 0.7338142718924525
    },
    {
        "t": 454,
        "value": 0.12328076868952631
    },
    {
        "t": 455,
        "value": 0.42789936070327705
    },
    {
        "t": 456,
        "value": 0.7640991477115034
    },
    {
        "t": 457,
        "value": 0.6201169846921074
    },
    {
        "t": 458,
        "value": 0.9406953519222472
    },
    {
        "t": 459,
        "value": 0.2621425247923266
    },
    {
        "t": 460,
        "value": 0.2267763449928606
    },
    {
        "t": 461,
        "value": 0.9698518101958136
    },
    {
        "t": 462,
        "value": 0.7816636872582162
    },
    {
        "t": 463,
        "value": 0.12986296580172707
    },
    {
        "t": 464,
        "value": 0.6472835829617193
    },
    {
        "t": 465,
        "value": 0.272917248392905
    },
    {
        "t": 466,
        "value": 0.253433927350466
    },
    {
        "t": 467,
        "value": 0.8694895857693452
    },
    {
        "t": 468,
        "value": 0.051263442222066025
    },
    {
        "t": 469,
        "value": 0.8730160142044686
    },
    {
        "t": 470,
        "value": 0.4663108085455734
    },
    {
        "t": 471,
        "value": 0.06855250636735488
    },
    {
        "t": 472,
        "value": 0.05816639866441842
    },
    {
        "t": 473,
        "value": 0.6826575972861492
    },
    {
        "t": 474,
        "value": 0.8817715353085571
    },
    {
        "t": 475,
        "value": 0.1180036244006335
    },
    {
        "t": 476,
        "value": 0.8143689275471482
    },
    {
        "t": 477,
        "value": 0.48545521578697737
    },
    {
        "t": 478,
        "value": 0.61056124965116
    },
    {
        "t": 479,
        "value": 0.027829767885110157
    },
    {
        "t": 480,
        "value": 0.028605966318827725
    },
    {
        "t": 481,
        "value": 0.4066543407931542
    },
    {
        "t": 482,
        "value": 0.09175537762751096
    },
    {
        "t": 483,
        "value": 0.022838135085157862
    },
    {
        "t": 484,
        "value": 0.5717218860718276
    },
    {
        "t": 485,
        "value": 0.3189967258526323
    },
    {
        "t": 486,
        "value": 0.7403532483429068
    },
    {
        "t": 487,
        "value": 0.7527428615305202
    },
    {
        "t": 488,
        "value": 0.6987429064834209
    },
    {
        "t": 489,
        "value": 0.3627673373686088
    },
    {
        "t": 490,
        "value": 0.021820601139047158
    },
    {
        "t": 491,
        "value": 0.632249432742866
    },
    {
        "t": 492,
        "value": 0.3367567011452306
    },
    {
        "t": 493,
        "value": 0.10915192908463
    },
    {
        "t": 494,
        "value": 0.3897968529052125
    },
    {
        "t": 495,
        "value": 0.7632020914583029
    },
    {
        "t": 496,
        "value": 0.45817934690147666
    },
    {
        "t": 497,
        "value": 0.2772986345105326
    },
    {
        "t": 498,
        "value": 0.5516829297963365
    },
    {
        "t": 499,
        "value": 0.1420895114647871
    }
]